starwarsdata/__init__.py
starwarsdata/starwars.py
starwarsdata-0.0.1.dist-info/LICENCE.txt
starwarsdata-0.0.1.dist-info/METADATA
starwarsdata-0.0.1.dist-info/WHEEL
starwarsdata-0.0.1.dist-info/top_level.txt
starwarsdata-0.0.1.dist-info/RECORD
