Metadata-Version: 2.1
Name: starwarsdata
Version: 0.0.1
Summary: This Python library interacts with the Star Wars Galaxy API, allowing users to retrieve information about characters, films, and more from the Star Wars universe.
Home-page: https://github.com/codewithwan/starwarsdata
Author: codewithwan
Author-email: <deezerxstore@gmail.com>
License: MIT
Keywords: data,starwars
Classifier: Development Status :: 1 - Planning
License-File: LICENCE.txt
